Metadata-Version: 1.0
Name: borys-peex
Version: 2.0
Summary: Incrediable and not reproducible python app!!!111
Home-page: https://long.long.time.ago.com
Author: borys
Author-email: borys@deathstar.com
License: MIT
Platform: UNKNOWN
